license/__init__.py
license/base.py
license/core.py
license/licenses.py
license/templates/AGPL-3.0
license/templates/AGPL-3.0+
license/templates/AGPL-3.0+__header
license/templates/AGPL-3.0__header
license/templates/Apache-1.0
license/templates/Apache-1.1
license/templates/Apache-2.0
license/templates/Apache-2.0__header
license/templates/BSD-2-Clause
license/templates/BSD-3-Clause
license/templates/GPL-2.0
license/templates/GPL-2.0+
license/templates/GPL-2.0+__header
license/templates/GPL-2.0__header
license/templates/GPL-3.0
license/templates/GPL-3.0+
license/templates/GPL-3.0+__header
license/templates/GPL-3.0__header
license/templates/LGPL-2.1
license/templates/LGPL-2.1+
license/templates/LGPL-2.1+__header
license/templates/LGPL-2.1__header
license/templates/LGPL-3.0
license/templates/LGPL-3.0+
license/templates/LGPL-3.0+__header
license/templates/LGPL-3.0__header
license/templates/MIT
license_win-0.1.2.dist-info/LICENSE.txt
license_win-0.1.2.dist-info/METADATA
license_win-0.1.2.dist-info/WHEEL
license_win-0.1.2.dist-info/top_level.txt
license_win-0.1.2.dist-info/RECORD
